{
  "DataEntityMetadataJson": {
    "[dbo].[CDM_REPORT_TYPE]": "{\"name\":\"[dbo].[CDM_REPORT_TYPE]\",\"title\":\"[dbo].[CDM_REPORT_TYPE]\",\"x-ms-permission\":\"read-write\",\"x-ms-capabilities\":{\"sortRestrictions\":{\"sortable\":true},\"filterRestrictions\":{\"filterable\":true},\"selectRestrictions\":{\"selectable\":true},\"filterFunctionSupport\":[\"lt\",\"le\",\"eq\",\"ne\",\"gt\",\"ge\",\"min\",\"max\",\"countdistinct\",\"add\",\"sub\",\"mul\",\"div\",\"mod\",\"negate\",\"now\",\"not\",\"and\",\"or\",\"day\",\"month\",\"year\",\"hour\",\"minute\",\"second\",\"date\",\"time\",\"totaloffsetminutes\",\"totalseconds\",\"round\",\"floor\",\"ceiling\",\"contains\",\"startswith\",\"endswith\",\"length\",\"indexof\",\"replace\",\"substring\",\"substringof\",\"tolower\",\"toupper\",\"trim\",\"concat\",\"sum\",\"min\",\"max\",\"average\",\"countdistinct\",\"null\"]},\"schema\":{\"type\":\"array\",\"items\":{\"type\":\"object\",\"required\":[\"REPORT_ID\"],\"properties\":{\"REPORT_ID\":{\"title\":\"REPORT_ID\",\"x-ms-capabilities\":{\"filterFunctions\":[\"lt\",\"le\",\"eq\",\"ne\",\"gt\",\"ge\",\"min\",\"max\",\"countdistinct\",\"add\",\"sub\",\"mul\",\"div\",\"mod\",\"negate\",\"sum\",\"average\"]},\"type\":\"integer\",\"format\":\"int32\",\"minimum\":-2147483648,\"maximum\":2147483647,\"x-ms-permission\":\"read-write\",\"x-ms-sort\":\"none\"},\"REPORT_NAME\":{\"title\":\"REPORT_NAME\",\"x-ms-capabilities\":{\"filterFunctions\":[\"lt\",\"le\",\"eq\",\"ne\",\"gt\",\"ge\",\"min\",\"max\",\"countdistinct\",\"contains\",\"startswith\",\"endswith\",\"length\",\"indexof\",\"replace\",\"substring\",\"substringof\",\"tolower\",\"toupper\",\"trim\",\"concat\"]},\"type\":\"string\",\"maxLength\":50,\"x-ms-permission\":\"read-write\",\"x-ms-sort\":\"none\"},\"FLOW_TYPE\":{\"title\":\"FLOW_TYPE\",\"x-ms-capabilities\":{\"filterFunctions\":[\"lt\",\"le\",\"eq\",\"ne\",\"gt\",\"ge\",\"min\",\"max\",\"countdistinct\",\"add\",\"sub\",\"mul\",\"div\",\"mod\",\"negate\",\"sum\",\"average\"]},\"type\":\"integer\",\"format\":\"int32\",\"minimum\":-2147483648,\"maximum\":2147483647,\"x-ms-permission\":\"read-write\",\"x-ms-sort\":\"none\"}}},\"x-ms-permission\":\"read-write\"}}"
  },
  "EntityName": "CDM_REPORT_TYPE",
  "TableName": "[dbo].[CDM_REPORT_TYPE]"
}