[
  {
    "ApiId": "/providers/microsoft.powerapps/apis/shared_sql",
    "CdpRevision": {
      "BaseUrl": "/v2",
      "LastChangedTimeString": "2024-03-01T19:30:31.3980000Z",
      "RevisionNumber": 2
    },
    "ConnectedDataSourceInfoNameMapping": {
      "57dfb1b5-7d79-4046-a4da-fd831d5befe1-KeyId": "KeyId",
      "ADJUSTED_CLAIM_ID": "ADJUSTED_CLAIM_ID",
      "ADJUSTMENT_CORRECT_COMPLETE_DATE": "ADJUSTMENT_CORRECT_COMPLETE_DATE",
      "ADJUSTMENT_CREATED": "ADJUSTMENT_CREATED",
      "ADJUSTMENT_NEEDED": "ADJUSTMENT_NEEDED",
      "ADJUSTMENT_REASON_CODE_I05_PRESENT": "ADJUSTMENT_REASON_CODE_I05_PRESENT",
      "ADMIT_DATE": "ADMIT_DATE",
      "AGE": "AGE",
      "ALLOWED_AMOUNT": "ALLOWED_AMOUNT",
      "AMOUNTPAID": "AMOUNTPAID",
      "ASIGN_DATE": "ASIGN_DATE",
      "ASSIGN_TO": "ASSIGN_TO",
      "AURORA_ACCOUNT": "AURORA_ACCOUNT",
      "AURORA_ADDITIONAL_NOTES": "AURORA_ADDITIONAL_NOTES",
      "AURORA_NOTES": "AURORA_NOTES",
      "BALANCE_DUE": "BALANCE_DUE",
      "BATCH_ID": "BATCH_ID",
      "BENEFIT_DESC": "BENEFIT_DESC",
      "BENEFIT_PLAN": "BENEFIT_PLAN",
      "BENEFITID": "BENEFITID",
      "BENEFITID_DESC": "BENEFITID_DESC",
      "BILL_TYPE": "BILL_TYPE",
      "BILLCLASSCODE": "BILLCLASSCODE",
      "BILLING_NPI": "BILLING_NPI",
      "BILLING_PROV_NAME": "BILLING_PROV_NAME",
      "BMS_NOTES": "BMS_NOTES",
      "BYMEDICARECLAIM": "BYMEDICARECLAIM",
      "BYNAMEPAID": "BYNAMEPAID",
      "BYSECONDARYCLAIM": "BYSECONDARYCLAIM",
      "CALL_CREATED": "CALL_CREATED",
      "CALLERID": "CALLERID",
      "CARRIERMEMID": "CARRIERMEMID",
      "CATEGORY": "CATEGORY",
      "CLAIM_END_TIME": "CLAIM_END_TIME",
      "CLAIM_START_TIME": "CLAIM_START_TIME",
      "CLAIM_STATUS_DESC": "CLAIM_STATUS_DESC",
      "CLAIM_STATUS_ID": "CLAIM_STATUS_ID",
      "CLAIM_TYPE": "CLAIM_TYPE",
      "CLAIM_x0023_": "CLAIM#",
      "CLAIMAMT": "CLAIMAMT",
      "CLAIMEDIT_REASON": "CLAIMEDIT_REASON",
      "CLAIMID": "CLAIMID",
      "CLAIMID_NEW": "CLAIMID_NEW",
      "CLAIMLINE": "CLAIMLINE",
      "CLAIMSOURCE": "CLAIMSOURCE",
      "CLEANDATE": "CLEANDATE",
      "CLIENT_ID": "CLIENT_ID",
      "CMSCONTRACTID": "CMSCONTRACTID",
      "COB_CSSB_CALCULATION_AMOUNT_OR_0_OR_NOT_CALCULATED": "COB_CSSB_CALCULATION_AMOUNT_OR_0_OR_NOT_CALCULATED",
      "COB_CUSTOM_MEMO_RECORD": "COB_CUSTOM_MEMO_RECORD",
      "COBAMT": "COBAMT",
      "COBELIGIBLEAMT": "COBELIGIBLEAMT",
      "COMMENT": "COMMENT",
      "COMMENTS": "COMMENTS",
      "CONNECT_EMERGENCY": "CONNECT_EMERGENCY",
      "CONTRACT_DESC": "CONTRACT_DESC",
      "CONTRACTID": "CONTRACTID",
      "CONTRACTID_DESC": "CONTRACTID_DESC",
      "CONTRACTPAID": "CONTRACTPAID",
      "CONTROLNMB": "CONTROLNMB",
      "CORRECTED_CLAIM_NEW_DAY_CLAIM_DENIED_AS_DUPLICATE": "CORRECTED_CLAIM_NEW_DAY_CLAIM_DENIED_AS_DUPLICATE",
      "DATE": "DATE",
      "DATE_OF_SERVICE": "DATE_OF_SERVICE",
      "DAYS_OPEN": "DAYS_OPEN",
      "DESCRIPTION": "DESCRIPTION",
      "DIAGNOSIS_7140_REMOVED_FROM_ADJUSTED_CLAIM": "DIAGNOSIS_7140_REMOVED_FROM_ADJUSTED_CLAIM",
      "DO_NOT_RECOUP_PROVIDER": "DO_NOT_RECOUP_PROVIDER",
      "DOB": "DOB",
      "DOSFROM": "DOSFROM",
      "DOSTO": "DOSTO",
      "ENDDATE": "ENDDATE",
      "ENROLL_EFFDATE": "ENROLL_EFFDATE",
      "ENROLL_TERM_DATE": "ENROLL_TERM_DATE",
      "EST_PATIENT_PAYMENT": "EST_PATIENT_PAYMENT",
      "EXPECTED_PAYMENT": "EXPECTED_PAYMENT",
      "EXTRA_FIELD_1": "EXTRA_FIELD_1",
      "EXTRA_FIELD_2": "EXTRA_FIELD_2",
      "EXTRA_FIELD_3": "EXTRA_FIELD_3",
      "EXTRA_FIELD_4": "EXTRA_FIELD_4",
      "EXTRA_FIELD_5": "EXTRA_FIELD_5",
      "FACILITYCODE": "FACILITYCODE",
      "FORMTYPE": "FORMTYPE",
      "FULLNAME": "FULLNAME",
      "ICARE_COB_REVIEW": "ICARE_COB_REVIEW",
      "IS_ASIGNED": "IS_ASIGNED",
      "IS_CLAIM_IN_PROCESS": "IS_CLAIM_IN_PROCESS",
      "IS_COMPLETED": "IS_COMPLETED",
      "IS_DELETED": "IS_DELETED",
      "IS_PAY": "IS_PAY",
      "IS_PEND": "IS_PEND",
      "IS_QUIRED": "IS_QUIRED",
      "IS_WRONGLY_PAID": "IS_WRONGLY_PAID",
      "LASTUPDATE": "LASTUPDATE",
      "LOB": "LOB",
      "LOGDATE": "LOGDATE",
      "LOGINID": "LOGINID",
      "MACESID_IMAGE": "MACESID_IMAGE",
      "MACESS_IMAGE_DX_7140_REMOVED": "MACESS_IMAGE_DX_7140_REMOVED",
      "MANUAL_COB": "MANUAL_COB",
      "MANUAL_PEND_DESCRIPTION": "MANUAL_PEND_DESCRIPTION",
      "MASTER_CLAIM_TSN_ID": "MASTER_CLAIM_TSN_ID",
      "MEDICARE_ALLOWED": "MEDICARE_ALLOWED",
      "MEDICARE_CLAIMID": "MEDICARE_CLAIMID",
      "MEDICARE_CO_INSURANCE": "MEDICARE_CO_INSURANCE",
      "MEDICARE_COPAY": "MEDICARE_COPAY",
      "MEDICARE_DEDUCTIABLE": "MEDICARE_DEDUCTIABLE",
      "MEDICARE_PAID": "MEDICARE_PAID",
      "MEMBER_NAME": "MEMBER_NAME",
      "MEMBER_SECONDARY_ID": "MEMBER_SECONDARY_ID",
      "MEMID": "MEMID",
      "MESSAGE": "MESSAGE",
      "METH2_CSSB_CALCULATION_AMOUNTS_MATCH": "METH2_CSSB_CALCULATION_AMOUNTS_MATCH",
      "METHOD_2_CALCULATION_AMOUNT": "METHOD_2_CALCULATION_AMOUNT",
      "MODCODE": "MODCODE",
      "MONTH": "MONTH",
      "NAME": "NAME",
      "NEW_ADJUSTMENT_COMPLETED": "NEW_ADJUSTMENT_COMPLETED",
      "NEW_ADJUSTMENT_NEEDED": "NEW_ADJUSTMENT_NEEDED",
      "NEW_ADJUSTMENT_PENDED": "NEW_ADJUSTMENT_PENDED",
      "NEW_ADJUSTMENT_VERIFIED_BY_SUE": "NEW_ADJUSTMENT_VERIFIED_BY_SUE",
      "NEW_CLAIM_ID": "NEW_CLAIM_ID",
      "NOTES": "NOTES",
      "NPI": "NPI",
      "ORGPOLICYID": "ORGPOLICYID",
      "PAID_DATE": "PAID_DATE",
      "PAIDDATE": "PAIDDATE",
      "PATIENT_TYPE": "PATIENT_TYPE",
      "PAY_DATE": "PAY_DATE",
      "PAYER_PAYMENT": "PAYER_PAYMENT",
      "PAYTO_PROVID": "PAYTO_PROVID",
      "PAYTO_PROVNAME": "PAYTO_PROVNAME",
      "PEND_COMMENT": "PEND_COMMENT",
      "PLANID": "PLANID",
      "PLANID_DESC": "PLANID_DESC",
      "PRINDIAG": "PRINDIAG",
      "PROG_DESCRIPTION": "PROG_DESCRIPTION",
      "PROGRAMID": "PROGRAMID",
      "PROGTYPE": "PROGTYPE",
      "PROV_NAME": "PROV_NAME",
      "PROV_ORGANIZATION": "PROV_ORGANIZATION",
      "PROVID": "PROVID",
      "PROVIDER": "PROVIDER",
      "PROVTYPE": "PROVTYPE",
      "PROVTYPE_DESC": "PROVTYPE_DESC",
      "QNX_TEMERGENCY": "QNX_TEMERGENCY",
      "QUERY": "QUERY",
      "QUERY_ANSWER": "QUERY_ANSWER",
      "QUERY_COMMENT": "QUERY_COMMENT",
      "QUERY_TO": "QUERY_TO",
      "QUEUE_ID": "QUEUE_ID",
      "RDESCRIPTION": "RDESCRIPTION",
      "REASON_FOR_NEW_ADJUSTMENT": "REASON_FOR_NEW_ADJUSTMENT",
      "REASON_FOR_PENDED_ADJUSTMENT": "REASON_FOR_PENDED_ADJUSTMENT",
      "RECOUP_AMOUNT": "RECOUP_AMOUNT",
      "RENDERING_NPI": "RENDERING_NPI",
      "RENDERING_PROV_NAME": "RENDERING_PROV_NAME",
      "REVCODE": "REVCODE",
      "RULE_DESCRIPTION": "RULE_DESCRIPTION",
      "RULEID": "RULEID",
      "RULEREASON_REPORTTEXT": "RULEREASON_REPORTTEXT",
      "SECONDARY_CLAIM_ALLOWED_AMOUNT": "SECONDARY_CLAIM_ALLOWED_AMOUNT",
      "SECONDARY_CLAIM_AMOUNT_PAID": "SECONDARY_CLAIM_AMOUNT_PAID",
      "SECONDARY_CLAIMID": "SECONDARY_CLAIMID",
      "SECONDARYID": "SECONDARYID",
      "SERV_PROVID": "SERV_PROVID",
      "SERV_PROVNAME": "SERV_PROVNAME",
      "SERVCODE": "SERVCODE",
      "SERVUNITS": "SERVUNITS",
      "SPECIALTYCODE": "SPECIALTYCODE",
      "SPECIALTYCODE_DESC": "SPECIALTYCODE_DESC",
      "SPONSOR": "SPONSOR",
      "SPONSOR_NAME": "SPONSOR_NAME",
      "STARTDATE": "STARTDATE",
      "STATUS": "STATUS",
      "SUBSCRIBER": "SUBSCRIBER",
      "TERMID": "TERMID",
      "TERMID_DESC": "TERMID_DESC",
      "TOTAL_CHARGE": "TOTAL_CHARGE",
      "TOTALAMT": "TOTALAMT",
      "TSN_INSERT_TIMESTAMP": "TSN_INSERT_TIMESTAMP",
      "UPDATEID": "UPDATEID",
      "UPID": "UPID",
      "USERID": "USERID",
      "YEAR": "YEAR"
    },
    "DatasetName": "LTIN399896%5cSQLEXPRESS,CDM_INT",
    "EncodeDataset": false,
    "IsSampleData": false,
    "IsWritable": false,
    "Name": "VW_CDM_CLAIM_DETAIL_TSN",
    "Type": "ConnectedDataSourceInfo"
  }
]